zerog_python_api/__init__.py
zerog_python_api/cli_tool
zerog_python_api/downloader.py
zerog_python_api/uploader.py
zerog_python_api-0.1.1.dist-info/METADATA
zerog_python_api-0.1.1.dist-info/WHEEL
zerog_python_api-0.1.1.dist-info/top_level.txt
zerog_python_api-0.1.1.dist-info/RECORD
