Metadata-Version: 2.1
Name: zerog_python_api
Version: 0.1.1
Requires-Dist: setuptools
